quokka/__init__.py
quokka/addresser.py
quokka/block.py
quokka/data.py
quokka/exc.py
quokka/executable.py
quokka/function.py
quokka/instruction.py
quokka/program.py
quokka/py.typed
quokka/quokka_pb2.py
quokka/reference.py
quokka/segment.py
quokka/structure.py
quokka/types.py
quokka/utils.py
quokka/analysis/__init__.py
quokka/analysis/arch.py
quokka/analysis/calling_convention.py
quokka/analysis/env.py
quokka/analysis/replacer.py
quokka/analysis/utils.py
quokka/backends/__init__.py
quokka/backends/capstone.py
quokka/backends/pypcode.py
quokka_project-1.0.5.dist-info/LICENSE
quokka_project-1.0.5.dist-info/METADATA
quokka_project-1.0.5.dist-info/WHEEL
quokka_project-1.0.5.dist-info/top_level.txt
quokka_project-1.0.5.dist-info/RECORD
