Metadata-Version: 2.1
Name: quokka-project
Version: 1.0.5
Summary: Quokka : A Fast and Accurate Binary Exporter
Home-page: https://github.com/quarkslab/quokka
Author: Alexis <dm> Challande
Author-email: achallande@quarkslab.com
License: Apache-2
Project-URL: Documentation, https://quarkslab.github.io/quokka/
Project-URL: Bug Tracker, https://github.com/quarkslab/quokka/issues
Project-URL: Source, https://github.com/quarkslab/quokka/
Platform: UNKNOWN
License-File: LICENSE
Requires-Dist: capstone (<5,>=4.0.2)
Requires-Dist: networkx (<3,>=2.4)
Requires-Dist: protobuf (<4,>=3.12.2)
Requires-Dist: pypcode (<1.1.0,>=1.0.7)
Provides-Extra: dev
Requires-Dist: black ; extra == 'dev'
Requires-Dist: ipython ; extra == 'dev'
Requires-Dist: flake8 ; extra == 'dev'
Requires-Dist: flake8-black ; extra == 'dev'
Requires-Dist: mypy ; extra == 'dev'
Requires-Dist: mypy-protobuf ; extra == 'dev'
Requires-Dist: nox ; extra == 'dev'
Provides-Extra: doc
Requires-Dist: mkdocs ; extra == 'doc'
Requires-Dist: mkdocs-material ; extra == 'doc'
Requires-Dist: mkdocstrings ; extra == 'doc'
Requires-Dist: mkdocstrings-python ; extra == 'doc'
Requires-Dist: mkdocs-literate-nav ; extra == 'doc'
Requires-Dist: mkdocs-gen-files ; extra == 'doc'
Requires-Dist: mkdocs-simple-hooks ; extra == 'doc'
Provides-Extra: test
Requires-Dist: pytest ; extra == 'test'
Requires-Dist: pytest-mock ; extra == 'test'
Requires-Dist: pytest-cov ; extra == 'test'
Requires-Dist: coverage[toml] ; extra == 'test'
